setup.py
m3u8_generator/__init__.py
m3u8_generator.egg-info/PKG-INFO
m3u8_generator.egg-info/SOURCES.txt
m3u8_generator.egg-info/dependency_links.txt
m3u8_generator.egg-info/top_level.txt