Metadata-Version: 1.0
Name: m3u8-generator
Version: 1.3
Summary: m3u8 playlist generator
Home-page: https://github.com/cambackup/m3u8-generator
Author: cambackup.com
Author-email: info@cambackup.com
License: UNKNOWN
Keywords: m3u8 playlist generator
Platform: UNKNOWN
